pychuck/__init__.py
pychuck/core.py
pychuck/gui.py
pychuck/unit.py
pychuck/util.py
pychuck/ui/main.py
pychuck/ui/pyaudicle.py
pychuck-1.0.1.dist-info/LICENSE
pychuck-1.0.1.dist-info/METADATA
pychuck-1.0.1.dist-info/WHEEL
pychuck-1.0.1.dist-info/entry_points.txt
pychuck-1.0.1.dist-info/top_level.txt
pychuck-1.0.1.dist-info/RECORD
