Metadata-Version: 2.1
Name: pychuck
Version: 1.0.1
Summary: Python implementation of music programming language Chuck
Author-email: Yikai Li <yikaili@stanford.edu>
Maintainer-email: Yikai Li <yikaili@stanford.edu>
License: Copyright (c) 2018 The Python Packaging Authority
Project-URL: documentation, https://pychuck.readthedocs.io/en/latest/
Project-URL: repository, https://github.com/42x00/pychuck.git
Keywords: chuck,music,programming,sound,synthesis
Classifier: Development Status :: 4 - Beta
Classifier: Programming Language :: Python
Requires-Python: >=3.7
License-File: LICENSE
Requires-Dist: numpy
Requires-Dist: networkx
Requires-Dist: sounddevice
Provides-Extra: cli
Provides-Extra: gui
Requires-Dist: PyQt6-QScintilla ; extra == 'gui'
